odoo/addons/rma_lot/README.rst
odoo/addons/rma_lot/__init__.py
odoo/addons/rma_lot/__manifest__.py
odoo/addons/rma_lot/i18n/it.po
odoo/addons/rma_lot/i18n/rma_lot.pot
odoo/addons/rma_lot/models/__init__.py
odoo/addons/rma_lot/models/rma.py
odoo/addons/rma_lot/models/rma_operation.py
odoo/addons/rma_lot/readme/CONFIGURE.md
odoo/addons/rma_lot/readme/CONTRIBUTORS.md
odoo/addons/rma_lot/readme/DESCRIPTION.md
odoo/addons/rma_lot/static/description/icon.png
odoo/addons/rma_lot/static/description/index.html
odoo/addons/rma_lot/tests/__init__.py
odoo/addons/rma_lot/tests/test_rma_lot.py
odoo/addons/rma_lot/views/rma.xml
odoo/addons/rma_lot/views/rma_operation.xml
odoo/addons/rma_lot/wizards/__init__.py
odoo/addons/rma_lot/wizards/stock_return_picking_line.py
odoo_addon_rma_lot-18.0.1.0.0.4.dist-info/METADATA
odoo_addon_rma_lot-18.0.1.0.0.4.dist-info/WHEEL
odoo_addon_rma_lot-18.0.1.0.0.4.dist-info/top_level.txt
odoo_addon_rma_lot-18.0.1.0.0.4.dist-info/RECORD
