Metadata-Version: 2.1
Name: odoo-addon-rma_lot
Version: 18.0.1.0.0.4
Requires-Python: >=3.10
Requires-Dist: odoo-addon-rma==18.0.*
Requires-Dist: odoo-addon-stock_picking_return_lot==18.0.*
Requires-Dist: odoo==18.0.*
Summary: Manage lot in RMA
Home-page: https://github.com/OCA/rma
License: AGPL-3
Author: ACSONE SA/NV,BCIM,Odoo Community Association (OCA)
Author-email: support@odoo-community.org
Classifier: Programming Language :: Python
Classifier: Framework :: Odoo
Classifier: Framework :: Odoo :: 18.0
Classifier: License :: OSI Approved :: GNU Affero General Public License v3
